pyfot/__init__.py
pyfot/api.py
pyfot/app_state.py
pyfot/data.py
pyfot/logger.py
pyfot/monitor.py
pyfot/pyfot.py
pyfot/ui.py
pyfot/utils.py
pyfot/assets/football.png
pyfot-1.3.1.dist-info/METADATA
pyfot-1.3.1.dist-info/WHEEL
pyfot-1.3.1.dist-info/entry_points.txt
pyfot-1.3.1.dist-info/top_level.txt
pyfot-1.3.1.dist-info/RECORD
