Metadata-Version: 2.2
Name: pyfot
Version: 1.3.1
Summary: PyFot is a TUI application for instant access to football matches schedule and team lineups right from your terminal.
Author: ayoub
Project-URL: Homepage, https://github.com/0x61796f7562/pyfot
Project-URL: Issues, https://github.com/0x61796f7562/pyfot/issues
Classifier: Operating System :: POSIX :: Linux
Classifier: Programming Language :: Python :: 3.9
Requires-Python: ~=3.9
Requires-Dist: chime==0.7.0
Requires-Dist: fake-useragent==1.5.1
Requires-Dist: plyer==2.1.0
Requires-Dist: pyjq==2.6.0
Requires-Dist: requests==2.32.3
Requires-Dist: urwid==2.6.16
Requires-Dist: dbus-python==1.3.2
